LICENSE
README.md
setup.cfg
setup.py
bundle/__init__.py
bundle/utilities/kedro/.gitignore
bundle/utilities/kedro/README.md
bundle/utilities/kedro/__init__.py
bundle/utilities/kedro/pyproject.toml
bundle/utilities/kedro/run.py
bundle/utilities/kedro/setup.cfg
bundle/utilities/kedro/conf/README.md
bundle/utilities/kedro/conf/base/catalog.yml
bundle/utilities/kedro/conf/base/logging.yml
bundle/utilities/kedro/conf/base/parameters.yml
bundle/utilities/kedro/conf/local/credentials.yml
bundle/utilities/kedro/data/01_raw/.gitkeep
bundle/utilities/kedro/data/01_raw/iris.csv
bundle/utilities/kedro/data/02_intermediate/.gitkeep
bundle/utilities/kedro/data/03_primary/.gitkeep
bundle/utilities/kedro/data/04_feature/.gitkeep
bundle/utilities/kedro/data/05_model_input/.gitkeep
bundle/utilities/kedro/data/06_models/.gitkeep
bundle/utilities/kedro/data/07_model_output/.gitkeep
bundle/utilities/kedro/data/08_reporting/.gitkeep
bundle/utilities/kedro/docs/source/conf.py
bundle/utilities/kedro/docs/source/index.rst
bundle/utilities/kedro/logs/.gitkeep
bundle/utilities/kedro/notebooks/.gitkeep
bundle/utilities/kedro/src/__init__.py
bundle/utilities/kedro/src/requirements.txt
bundle/utilities/kedro/src/setup.py
bundle/utilities/kedro/src/meltano_kedro/__init__.py
bundle/utilities/kedro/src/meltano_kedro/__main__.py
bundle/utilities/kedro/src/meltano_kedro/nodes.py
bundle/utilities/kedro/src/meltano_kedro/pipeline.py
bundle/utilities/kedro/src/meltano_kedro/pipeline_registry.py
bundle/utilities/kedro/src/meltano_kedro/settings.py
bundle/utilities/kedro/src/tests/__init__.py
bundle/utilities/kedro/src/tests/test_pipeline.py
bundle/utilities/kedro/src/tests/test_run.py
files_kedro.egg-info/PKG-INFO
files_kedro.egg-info/SOURCES.txt
files_kedro.egg-info/dependency_links.txt
files_kedro.egg-info/top_level.txt